{
	"required": true,
	"package": "com.example.emeraldmod.mixin",
	"compatibilityLevel": "JAVA_21",
	"mixins": [
		"EntityMixin",
		"EntityPowderSnowCheckMixin",
		"FallingBlockEntityMixin",
		"FallingBlockMixin",
		"HorseEntityPowderSnowMixin",
		"ItemStackMixin",
		"LivingEntityMixin",
		"LivingEntityNegativeImmunityMixin",
		"PlayerEntitySilentMixin",
		"PowderSnowBlockMixin",
		"SculkSensorBlockMixin",
		"SculkShriekerBlockMixin",
		"ServerWorldMixin",
		"TripwireHookBlockMixin"
	],
	"injectors": {
		"defaultRequire": 1
	},
	"overwrites": {
		"requireAnnotations": true
	}
}